mcp_server_ocr/__init__.py
mcp_server_ocr/__main__.py
mcp_server_ocr/server.py
mcp_server_ocr-0.1.0.dist-info/METADATA
mcp_server_ocr-0.1.0.dist-info/WHEEL
mcp_server_ocr-0.1.0.dist-info/entry_points.txt
mcp_server_ocr-0.1.0.dist-info/RECORD
