Metadata-Version: 2.4
Name: mcp-server-ocr
Version: 0.1.0
Summary: A Model Context Protocol server providing OCR capabilities for images and videos using GLM-4.1V-Thinking-Flash
Author: OCR MCP Server
License: MIT
Keywords: glm,llm,mcp,ocr,vision
Classifier: Development Status :: 4 - Beta
Classifier: Intended Audience :: Developers
Classifier: License :: OSI Approved :: MIT License
Classifier: Programming Language :: Python :: 3
Classifier: Programming Language :: Python :: 3.10
Requires-Python: >=3.10
Requires-Dist: mcp>=1.1.3
Requires-Dist: pillow>=10.0.0
Requires-Dist: pydantic>=2.0.0
Requires-Dist: zhipuai>=2.0.0
